Metadata-Version: 2.1
Name: remoteCLI
Version: 0.2
Summary: 对 socket 简单的封装
Home-page: https://github.com/rmb122/remoteCLI
Author: rmb122
Author-email: pypi@rmb122.com
License: GPLv3.0
Keywords: remote,ctf
Platform: all
Requires-Python: >=3.4.0
